README.md
setup.cfg
setup.py
export/__init__.py
export/file_path.py
export/output_file.py
fingerscan/__init__.py
fingerscan/fingerscan.py
fingerscan/requirements.txt
fingerscan/test.py
fingerscan.egg-info/PKG-INFO
fingerscan.egg-info/SOURCES.txt
fingerscan.egg-info/dependency_links.txt
fingerscan.egg-info/entry_points.txt
fingerscan.egg-info/requires.txt
fingerscan.egg-info/top_level.txt
fingerscan/export/__init__.py
fingerscan/export/file_path.py
fingerscan/export/output_file.py
fingerscan/export/config/cdn_ip_cidr.json
fingerscan/export/config/finger.json
fingerscan/export/config/iotscan.json
fingerscan/export/config/ip2region.xdb
fingerscan/util/__init__.py
fingerscan/util/agent/__init__.py
fingerscan/util/agent/agent.py
fingerscan/util/core/__init__.py
fingerscan/util/core/cdn/__init__.py
fingerscan/util/core/cdn/cdn.py
fingerscan/util/core/cert/__init__.py
fingerscan/util/core/cert/ssl.py
fingerscan/util/core/finger/__init__.py
fingerscan/util/core/finger/finger.py
fingerscan/util/core/finger/finger_v2.py
fingerscan/util/core/finger/tcp_finger.py
fingerscan/util/core/icon/__init__.py
fingerscan/util/core/icon/get_icon.py
fingerscan/util/core/icp/__init__.py
fingerscan/util/core/icp/get_icp.py
fingerscan/util/core/ip/__init__.py
fingerscan/util/core/ip/get_ip_info.py
fingerscan/util/core/ip/xdbSearcher.py
fingerscan/util/core/tcp_requests/__init__.py
fingerscan/util/core/tcp_requests/dm_databases_tcp.py
fingerscan/util/core/tcp_requests/redis_tcp.py
fingerscan/util/socket/__init__.py
fingerscan/util/socket/redis_tcp.py
fingerscan/util/socket/req.py
fingerscan/util/socket/socket.py
util/__init__.py
util/agent/__init__.py
util/agent/agent.py
util/core/__init__.py
util/core/cdn/__init__.py
util/core/cdn/cdn.py
util/core/cert/__init__.py
util/core/cert/ssl.py
util/core/finger/__init__.py
util/core/finger/finger_v2.py
util/core/finger/tcp_finger.py
util/core/icon/__init__.py
util/core/icon/get_icon.py
util/core/icp/__init__.py
util/core/icp/get_icp.py
util/core/ip/__init__.py
util/core/ip/get_ip_info.py
util/core/ip/xdbSearcher.py
util/core/tcp_requests/__init__.py
util/core/tcp_requests/dm_databases_tcp.py
util/core/tcp_requests/redis_tcp.py
util/socket/__init__.py
