Metadata-Version: 2.1
Name: fingerscan
Version: 1.2.4
Summary: 指纹识别开发测试版本
Home-page: https://github.com/expzhizhuo
Author: zhizhuo
Author-email: zhizhuoshuma@163.com
Requires-Python: >=3.8
Requires-Dist: requests
Requires-Dist: colorama
Requires-Dist: mmh3
Requires-Dist: urllib3
Requires-Dist: pyfiglet
Requires-Dist: termcolor
Requires-Dist: openpyxl
Requires-Dist: poc-tool
Requires-Dist: alive-progress
Requires-Dist: pyOpenSSL
Requires-Dist: beautifulsoup4
